[
  {
    "movieId": 31,
    "title": "Dangerous Minds (1995)"
  },
  {
    "movieId": 32,
    "title": "Twelve Monkeys (a.k.a. 12 Monkeys) (1995)"
  },
  {
    "movieId": 39,
    "title": "Clueless (1995)"
  },
  {
    "movieId": 80,
    "title": "White Balloon, The (Badkonake sefid) (1995)"
  },
  {
    "movieId": 177,
    "title": "Lord of Illusions (1995)"
  },
  {
    "movieId": 204,
    "title": "Under Siege 2: Dark Territory (1995)"
  },
  {
    "movieId": 356,
    "title": "Forrest Gump (1994)"
  },
  {
    "movieId": 474,
    "title": "In the Line of Fire (1993)"
  },
  {
    "movieId": 541,
    "title": "Blade Runner (1982)"
  },
  {
    "movieId": 587,
    "title": "Ghost (1990)"
  },
  {
    "movieId": 750,
    "title": "Dr. Strangelove or: How I Learned to Stop Worrying and Love the Bomb (1964)"
  },
  {
    "movieId": 778,
    "title": "Trainspotting (1996)"
  },
  {
    "movieId": 1101,
    "title": "Top Gun (1986)"
  },
  {
    "movieId": 1179,
    "title": "Grifters, The (1990)"
  },
  {
    "movieId": 1199,
    "title": "Brazil (1985)"
  },
  {
    "movieId": 1203,
    "title": "12 Angry Men (1957)"
  },
  {
    "movieId": 1258,
    "title": "Shining, The (1980)"
  },
  {
    "movieId": 1278,
    "title": "Young Frankenstein (1974)"
  },
  {
    "movieId": 1408,
    "title": "Last of the Mohicans, The (1992)"
  },
  {
    "movieId": 1588,
    "title": "George of the Jungle (1997)"
  },
  {
    "movieId": 1610,
    "title": "Hunt for Red October, The (1990)"
  },
  {
    "movieId": 2020,
    "title": "Dangerous Liaisons (1988)"
  },
  {
    "movieId": 2102,
    "title": "Steamboat Willie (1928)"
  },
  {
    "movieId": 2355,
    "title": "Bug's Life, A (1998)"
  },
  {
    "movieId": 2513,
    "title": "Pet Sematary (1989)"
  },
  {
    "movieId": 2682,
    "title": "Limbo (1999)"
  },
  {
    "movieId": 2987,
    "title": "Who Framed Roger Rabbit? (1988)"
  },
  {
    "movieId": 3167,
    "title": "Carnal Knowledge (1971)"
  },
  {
    "movieId": 3847,
    "title": "Ilsa, She Wolf of the SS (1974)"
  },
  {
    "movieId": 3868,
    "title": "Naked Gun: From the Files of Police Squad!, The (1988)"
  },
  {
    "movieId": 4351,
    "title": "Point Break (1991)"
  },
  {
    "movieId": 4816,
    "title": "Zoolander (2001)"
  },
  {
    "movieId": 5065,
    "title": "Mothman Prophecies, The (2002)"
  },
  {
    "movieId": 5643,
    "title": "Powaqqatsi (1988)"
  },
  {
    "movieId": 6503,
    "title": "Charlie's Angels: Full Throttle (2003)"
  },
  {
    "movieId": 6952,
    "title": "Gothika (2003)"
  },
  {
    "movieId": 6953,
    "title": "21 Grams (2003)"
  },
  {
    "movieId": 6957,
    "title": "Bad Santa (2003)"
  },
  {
    "movieId": 8641,
    "title": "Anchorman: The Legend of Ron Burgundy (2004)"
  },
  {
    "movieId": 26736,
    "title": "Riki-Oh: The Story of Ricky (Lik Wong) (1991)"
  },
  {
    "movieId": 42761,
    "title": "Casper Meets Wendy (1998)"
  },
  {
    "movieId": 48394,
    "title": "Pan's Labyrinth (Laberinto del fauno, El) (2006)"
  },
  {
    "movieId": 50872,
    "title": "Ratatouille (2007)"
  },
  {
    "movieId": 51662,
    "title": "300 (2007)"
  },
  {
    "movieId": 55276,
    "title": "Michael Clayton (2007)"
  },
  {
    "movieId": 77866,
    "title": "Robin Hood (2010)"
  },
  {
    "movieId": 111362,
    "title": "X-Men: Days of Future Past (2014)"
  },
  {
    "movieId": 117590,
    "title": "Horrible Bosses 2 (2014)"
  },
  {
    "movieId": 119155,
    "title": "Night at the Museum: Secret of the Tomb (2014)"
  }
]